concrete/__init__.py
concrete/ml/__init__.py
concrete/ml/common/__init__.py
concrete/ml/common/check_inputs.py
concrete/ml/common/debugging/__init__.py
concrete/ml/common/debugging/custom_assert.py
concrete/ml/common/serialization/__init__.py
concrete/ml/common/serialization/decoder.py
concrete/ml/common/serialization/dumpers.py
concrete/ml/common/serialization/encoder.py
concrete/ml/common/serialization/loaders.py
concrete/ml/common/utils.py
concrete/ml/deployment/__init__.py
concrete/ml/deployment/_utils.py
concrete/ml/deployment/fhe_client_server.py
concrete/ml/onnx/__init__.py
concrete/ml/onnx/convert.py
concrete/ml/onnx/onnx_impl_utils.py
concrete/ml/onnx/onnx_model_manipulations.py
concrete/ml/onnx/onnx_utils.py
concrete/ml/onnx/ops_impl.py
concrete/ml/pandas/__init__.py
concrete/ml/pandas/_client_server_files/client.zip
concrete/ml/pandas/_client_server_files/server.zip
concrete/ml/pandas/_development.py
concrete/ml/pandas/_operators.py
concrete/ml/pandas/_processing.py
concrete/ml/pandas/_utils.py
concrete/ml/pandas/client_engine.py
concrete/ml/pandas/dataframe.py
concrete/ml/pytest/__init__.py
concrete/ml/pytest/torch_models.py
concrete/ml/pytest/utils.py
concrete/ml/quantization/__init__.py
concrete/ml/quantization/base_quantized_op.py
concrete/ml/quantization/linear_op_glwe_backend.py
concrete/ml/quantization/post_training.py
concrete/ml/quantization/qat_quantizers.py
concrete/ml/quantization/quantized_module.py
concrete/ml/quantization/quantized_module_passes.py
concrete/ml/quantization/quantized_ops.py
concrete/ml/quantization/quantizers.py
concrete/ml/search_parameters/__init__.py
concrete/ml/search_parameters/p_error_search.py
concrete/ml/sklearn/__init__.py
concrete/ml/sklearn/_fhe_training_utils.py
concrete/ml/sklearn/base.py
concrete/ml/sklearn/glm.py
concrete/ml/sklearn/linear_model.py
concrete/ml/sklearn/neighbors.py
concrete/ml/sklearn/qnn.py
concrete/ml/sklearn/qnn_module.py
concrete/ml/sklearn/rf.py
concrete/ml/sklearn/svm.py
concrete_ml-1.9.0.dist-info/LICENSE
concrete_ml-1.9.0.dist-info/METADATA
concrete_ml-1.9.0.dist-info/WHEEL
concrete_ml-1.9.0.dist-info/RECORD
