Metadata-Version: 2.1
Name: concrete-ml
Version: 1.9.0
Summary: Concrete ML is an open-source set of tools which aims to simplify the use of fully homomorphic encryption (FHE) for data scientists.
Home-page: https://zama.ai/concrete-ml/
License: BSD-3-Clause-Clear
Keywords: FHE,homomorphic encryption,privacy,security
Author: Zama
Author-email: hello@zama.ai
Requires-Python: >=3.8.1,<3.13
Classifier: License :: Other/Proprietary License
Classifier: Programming Language :: Python :: 3
Classifier: Programming Language :: Python :: 3.9
Classifier: Programming Language :: Python :: 3.10
Classifier: Programming Language :: Python :: 3.11
Classifier: Programming Language :: Python :: 3.12
Classifier: Programming Language :: Python :: 3.8
Classifier: Topic :: Scientific/Engineering
Classifier: Topic :: Scientific/Engineering :: Artificial Intelligence
Classifier: Topic :: Scientific/Engineering :: Mathematics
Classifier: Topic :: Security
Classifier: Topic :: Security :: Cryptography
Classifier: Topic :: Software Development :: Compilers
Requires-Dist: brevitas (==0.10.2)
Requires-Dist: concrete-ml-extensions (==0.1.9)
Requires-Dist: concrete-python (==2.10.0)
Requires-Dist: hummingbird-ml[onnx] (==0.4.11)
Requires-Dist: numpy (==1.23.5) ; python_version < "3.9"
Requires-Dist: numpy (==1.26.4) ; python_full_version >= "3.9.0"
Requires-Dist: onnx (==1.17.0)
Requires-Dist: onnxoptimizer (==0.3.13)
Requires-Dist: onnxruntime (==1.18)
Requires-Dist: pandas (==2.0.3) ; python_version < "3.12"
Requires-Dist: pandas (>=2.1.1) ; python_version >= "3.12"
Requires-Dist: protobuf (==3.20.3) ; python_full_version <= "3.11.0"
Requires-Dist: protobuf (>=5.28.3,<6.0.0) ; python_full_version > "3.11.0"
Requires-Dist: scikit-learn (==1.1.3) ; python_version < "3.9"
Requires-Dist: scikit-learn (==1.5.0) ; python_full_version >= "3.9.0"
Requires-Dist: scipy (==1.10.1) ; python_version == "3.8"
Requires-Dist: scipy (>=1.10.1) ; python_full_version > "3.8.0"
Requires-Dist: setuptools (==75.3.0)
Requires-Dist: skops (==0.5.0)
Requires-Dist: skorch (==0.11.0)
Requires-Dist: torch (==2.2.2) ; platform_system == "Darwin" and platform_machine != "arm64"
Requires-Dist: torch (==2.3.1) ; platform_system != "Darwin" or platform_machine == "arm64"
Requires-Dist: typing-extensions (>=4.5.0,<5.0.0)
Requires-Dist: xgboost (==1.6.2)
Project-URL: Bug Tracker, https://github.com/zama-ai/concrete-ml/issues
Project-URL: Documentation, http://docs.zama.ai/concrete-ml/
Project-URL: Repository, https://github.com/zama-ai/concrete-ml
Project-URL: README, https://github.com/zama-ai/concrete-ml/blob/main/README.md
